Workbook

Sheet Instructions
B2: Budget & Revenue Monitoring Dashboard
B3: Track project budget consumption, revenue, and Earned Value (EVM) in one workbook.
B5: How this workbook is organized
B6: Setup | C6: Enter your project name, total approved budget (BAC), total contract/expected revenue, and project dates. Everything else calculates from these.
B7: Monthly Tracking | C7: Enter ONE row per month: planned % complete, actual % complete, consumed budget (actual cost) for the month, and revenue invoiced/received for the month. All Earned Value metrics (PV, EV, AC, CV, SV, CPI, SPI) and profit figures calculate automatically.
B8: Dashboard | C8: Live KPI cards and charts pulled from Monthly Tracking - Budget vs Consumed vs Revenue, the EVM S-curve (PV/EV/AC), CPI & SPI trend, and cumulative profit. Nothing to edit here.
B10: Color legend
B11: Blue text on yellow fill | C11: Cells you fill in (inputs).
B12: Black text | C12: Formulas - do not overwrite, they recalculate automatically.
B13: Green text | C13: Links pulling values from another sheet.
B15: Key terms (Earned Value Management)
B16: PV - Planned Value | C16: Budgeted cost of work that SHOULD be done by now = Total Budget x Planned % Complete.
B17: EV - Earned Value | C17: Budgeted cost of work ACTUALLY done = Total Budget x Actual % Complete. This is your project's 'earned value'.
B18: AC - Actual Cost | C18: Money actually spent so far = Consumed Budget (cumulative).
B19: CV - Cost Variance | C19: EV - AC. Positive = under budget for the work completed. Negative = overspending.
B20: SV - Schedule Variance | C20: EV - PV. Positive = ahead of schedule. Negative = behind schedule.
B21: CPI - Cost Performance Index | C21: EV / AC. Above 1.00 = spending efficiently. Below 1.00 = over budget for work done.
B22: SPI - Schedule Performance Index | C22: EV / PV. Above 1.00 = ahead of schedule. Below 1.00 = behind schedule.
B23: Revenue vs Consumed Budget | C23: Revenue (invoiced/earned) minus Consumed Budget (actual cost) = Gross Profit for the project to date.
B25: To start | C25: Go to the 'Setup' sheet and enter your project details, then open 'Monthly Tracking' and replace the sample rows (highlighted) with your own months and figures.

Sheet Setup
B2: Project Setup
B3: Fill in the yellow cells. These values drive every calculation in the workbook.
B5: Project Name | C5: Riverside Client Portal | D5: Free text label shown on the Dashboard.
B6: Currency | C6: USD | D6: Label only, e.g. USD, EUR, BDT.
B7: Project Start Date | C7: 46023 | D7: First month of the project.
B8: Planned End Date | C8: 46387 | D8: Scheduled completion date.
B9: Total Approved Budget (BAC) | C9: 240000 | D9: Budget at Completion - total approved project budget.
B10: Total Contract / Expected Revenue | C10: 300000 | D10: Total revenue you expect to invoice/earn for this project.

Sheet Monthly Tracking
A2: Monthly Budget, Revenue & Earned Value Tracking
A3: Enter your own months and figures in the yellow columns (A-D, F). Everything else is calculated.
A5: Month | B5: Planned % Complete (cumulative) | C5: Actual % Complete (cumulative) | D5: Consumed Budget this month (Actual Cost) | E5: Consumed Budget cumulative (AC) | F5: Revenue Invoiced this month | G5: Revenue cumulative | H5: Planned Value (PV) | I5: Earned Value (EV) | J5: Cost Variance (CV = EV-AC) | K5: Schedule Variance (SV = EV-PV) | L5: CPI (EV/AC) | M5: SPI (EV/PV) | N5: Gross Profit (Revenue - AC) | O5: Profit Margin %
A6: Jan 2026 | B6: 0.08 | C6: 0.07 | D6: 18000 | E6: =D6 -> 18000 | F6: 22000 | G6: =F6 -> 22000 | H6: =Setup!$C$9*B6 -> 19200 | I6: =Setup!$C$9*C6 -> 16800 | J6: =I6-E6 -> -1200 | K6: =I6-H6 -> -2400 | L6: =IFERROR(I6/E6,"-") -> 0.93333333 | M6: =IFERROR(I6/H6,"-") -> 0.875 | N6: =G6-E6 -> 4000 | O6: =IFERROR(N6/G6,"-") -> 0.18181818
A7: Feb 2026 | B7: 0.17 | C7: 0.15 | D7: 20000 | E7: =E6+D7 -> 38000 | F7: 25000 | G7: =G6+F7 -> 47000 | H7: =Setup!$C$9*B7 -> 40800 | I7: =Setup!$C$9*C7 -> 36000 | J7: =I7-E7 -> -2000 | K7: =I7-H7 -> -4800 | L7: =IFERROR(I7/E7,"-") -> 0.94736842 | M7: =IFERROR(I7/H7,"-") -> 0.88235294 | N7: =G7-E7 -> 9000 | O7: =IFERROR(N7/G7,"-") -> 0.19148936
A8: Mar 2026 | B8: 0.25 | C8: 0.24 | D8: 19500 | E8: =E7+D8 -> 57500 | F8: 24000 | G8: =G7+F8 -> 71000 | H8: =Setup!$C$9*B8 -> 60000 | I8: =Setup!$C$9*C8 -> 57600 | J8: =I8-E8 -> 100 | K8: =I8-H8 -> -2400 | L8: =IFERROR(I8/E8,"-") -> 1.0017391 | M8: =IFERROR(I8/H8,"-") -> 0.96 | N8: =G8-E8 -> 13500 | O8: =IFERROR(N8/G8,"-") -> 0.19014085
A9: Apr 2026 | B9: 0.35 | C9: 0.3 | D9: 21000 | E9: =E8+D9 -> 78500 | F9: 20000 | G9: =G8+F9 -> 91000 | H9: =Setup!$C$9*B9 -> 84000 | I9: =Setup!$C$9*C9 -> 72000 | J9: =I9-E9 -> -6500 | K9: =I9-H9 -> -12000 | L9: =IFERROR(I9/E9,"-") -> 0.91719745 | M9: =IFERROR(I9/H9,"-") -> 0.85714286 | N9: =G9-E9 -> 12500 | O9: =IFERROR(N9/G9,"-") -> 0.13736264
A10: May 2026 | B10: 0.45 | C10: 0.4 | D10: 20500 | E10: =E9+D10 -> 99000 | F10: 26000 | G10: =G9+F10 -> 117000 | H10: =Setup!$C$9*B10 -> 108000 | I10: =Setup!$C$9*C10 -> 96000 | J10: =I10-E10 -> -3000 | K10: =I10-H10 -> -12000 | L10: =IFERROR(I10/E10,"-") -> 0.96969697 | M10: =IFERROR(I10/H10,"-") -> 0.88888889 | N10: =G10-E10 -> 18000 | O10: =IFERROR(N10/G10,"-") -> 0.15384615
A11: Jun 2026 | B11: 0.55 | C11: 0.52 | D11: 22000 | E11: =E10+D11 -> 121000 | F11: 28000 | G11: =G10+F11 -> 145000 | H11: =Setup!$C$9*B11 -> 132000 | I11: =Setup!$C$9*C11 -> 124800 | J11: =I11-E11 -> 3800 | K11: =I11-H11 -> -7200 | L11: =IFERROR(I11/E11,"-") -> 1.031405 | M11: =IFERROR(I11/H11,"-") -> 0.94545455 | N11: =G11-E11 -> 24000 | O11: =IFERROR(N11/G11,"-") -> 0.16551724
A13: Latest (Project-to-date) | E13: =E11 -> 121000 | G13: =G11 -> 145000 | H13: =H11 -> 132000 | I13: =I11 -> 124800 | J13: =J11 -> 3800 | K13: =K11 -> -7200 | L13: =L11 -> 1.031405 | M13: =M11 -> 0.94545455 | N13: =N11 -> 24000 | O13: =O11 -> 0.16551724

Sheet Dashboard
B2: Project Dashboard
B3: ="Project: "&Setup!$C$5&" | As of: "&'Monthly Tracking'!A11&" | Currency: "&Setup!$C$6 -> Project: Riverside Client Portal | As of: Jun 2026 | Currency: USD
B5: Total Budget (BAC) | D5: Consumed Budget (AC) | F5: Revenue Earned | H5: Gross Profit
B6: =Setup!$C$9 -> 240000 | D6: ='Monthly Tracking'!$E$13 -> 121000 | F6: ='Monthly Tracking'!$G$13 -> 145000 | H6: ='Monthly Tracking'!$N$13 -> 24000
B8: Earned Value (EV) | D8: Cost Variance (CV) | F8: CPI (Cost Perf. Index) | H8: SPI (Sched. Perf. Index)
B9: ='Monthly Tracking'!$I$13 -> 124800 | D9: ='Monthly Tracking'!$J$13 -> 3800 | F9: ='Monthly Tracking'!$L$13 -> 1.031405 | H9: ='Monthly Tracking'!$M$13 -> 0.94545455
B12: Month-by-Month Comparison
B13: Month | C13: Planned Value (PV) | D13: Consumed Budget (AC) | E13: Revenue Earned | F13: Earned Value (EV)
B14: ='Monthly Tracking'!A6 -> Jan 2026 | C14: ='Monthly Tracking'!H6 -> 19200 | D14: ='Monthly Tracking'!E6 -> 18000 | E14: ='Monthly Tracking'!G6 -> 22000 | F14: ='Monthly Tracking'!I6 -> 16800
B15: ='Monthly Tracking'!A7 -> Feb 2026 | C15: ='Monthly Tracking'!H7 -> 40800 | D15: ='Monthly Tracking'!E7 -> 38000 | E15: ='Monthly Tracking'!G7 -> 47000 | F15: ='Monthly Tracking'!I7 -> 36000
B16: ='Monthly Tracking'!A8 -> Mar 2026 | C16: ='Monthly Tracking'!H8 -> 60000 | D16: ='Monthly Tracking'!E8 -> 57500 | E16: ='Monthly Tracking'!G8 -> 71000 | F16: ='Monthly Tracking'!I8 -> 57600
B17: ='Monthly Tracking'!A9 -> Apr 2026 | C17: ='Monthly Tracking'!H9 -> 84000 | D17: ='Monthly Tracking'!E9 -> 78500 | E17: ='Monthly Tracking'!G9 -> 91000 | F17: ='Monthly Tracking'!I9 -> 72000
B18: ='Monthly Tracking'!A10 -> May 2026 | C18: ='Monthly Tracking'!H10 -> 108000 | D18: ='Monthly Tracking'!E10 -> 99000 | E18: ='Monthly Tracking'!G10 -> 117000 | F18: ='Monthly Tracking'!I10 -> 96000
B19: ='Monthly Tracking'!A11 -> Jun 2026 | C19: ='Monthly Tracking'!H11 -> 132000 | D19: ='Monthly Tracking'!E11 -> 121000 | E19: ='Monthly Tracking'!G11 -> 145000 | F19: ='Monthly Tracking'!I11 -> 124800
